setup.py
happymongo/__init__.py
happymongo.egg-info/PKG-INFO
happymongo.egg-info/SOURCES.txt
happymongo.egg-info/dependency_links.txt
happymongo.egg-info/requires.txt
happymongo.egg-info/top_level.txt